audio2splitted/__init__.py
audio2splitted/audio2splitted.py
audio2splitted/utils.py
audio2splitted-2024.10.31.dist-info/METADATA
audio2splitted-2024.10.31.dist-info/WHEEL
audio2splitted-2024.10.31.dist-info/entry_points.txt
audio2splitted-2024.10.31.dist-info/top_level.txt
audio2splitted-2024.10.31.dist-info/RECORD
